cpu_scheduler/__init__.py
cpu_scheduler/algorithms.py
cpu_scheduler-1.0.dist-info/METADATA
cpu_scheduler-1.0.dist-info/WHEEL
cpu_scheduler-1.0.dist-info/top_level.txt
cpu_scheduler-1.0.dist-info/RECORD
