Metadata-Version: 2.1
Name: cpu-scheduler
Version: 1.0
Summary: A Python library for CPU scheduling algorithms
Home-page: https://github.com/Nitish-Naik/schedulipy
Author: Nitish Naik
Author-email: nitishnaik2022@gmail.com
Classifier: Programming Language :: Python :: 3
Classifier: License :: OSI Approved :: MIT License
Classifier: Operating System :: OS Independent
Requires-Python: >=3.6
